oakemu/__init__.py
oakemu/assemblies/MrKWatkins.Ast.dll
oakemu/assemblies/MrKWatkins.OakAsm.Disassembly.dll
oakemu/assemblies/MrKWatkins.OakAsm.IO.ZXSpectrum.dll
oakemu/assemblies/MrKWatkins.OakAsm.IO.dll
oakemu/assemblies/MrKWatkins.OakAsm.Z80.dll
oakemu/assemblies/MrKWatkins.OakAsm.dll
oakemu/assemblies/MrKWatkins.OakEmu.Cpus.Z80.dll
oakemu/assemblies/MrKWatkins.OakEmu.Cpus.dll
oakemu/assemblies/MrKWatkins.OakEmu.Machines.ZXSpectrum.Games.dll
oakemu/assemblies/MrKWatkins.OakEmu.Machines.ZXSpectrum.dll
oakemu/assemblies/MrKWatkins.OakEmu.dll
oakemu/machines/__init__.py
oakemu/machines/zxspectrum/__init__.py
oakemu/machines/zxspectrum/deathchase.py
oakemu/machines/zxspectrum/game.py
oakemu/machines/zxspectrum/gameresult.py
oakemu/machines/zxspectrum/keyboard.py
oakemu/machines/zxspectrum/keys.py
oakemu/machines/zxspectrum/manicminer.py
oakemu/machines/zxspectrum/memory.py
oakemu/machines/zxspectrum/recorder.py
oakemu/machines/zxspectrum/registers.py
oakemu/machines/zxspectrum/stepresult.py
oakemu/machines/zxspectrum/z80.py
oakemu/machines/zxspectrum/zxspectrum.py
oakemu-0.0.18.dist-info/LICENCE
oakemu-0.0.18.dist-info/METADATA
oakemu-0.0.18.dist-info/WHEEL
oakemu-0.0.18.dist-info/RECORD
