Metadata-Version: 2.1
Name: oakemu
Version: 0.0.18
Summary: Python wrappers for the OakEmu project.
Home-page: https://www.mrkwatkins.co.uk
License: MIT
Author: MrKWatkins
Author-email: mrkwatkins@gmail.com
Requires-Python: >=3.11,<3.13
Classifier: Development Status :: 3 - Alpha
Classifier: License :: OSI Approved :: MIT License
Classifier: Programming Language :: Python :: 3
Classifier: Programming Language :: Python :: 3.11
Classifier: Programming Language :: Python :: 3.12
Requires-Dist: pythonnet (>=3.0.4,<4.0.0)
Project-URL: Repository, https://github.com/MrKWatkins/OakEmu-Python
